MANIFEST.in
README.txt
setup.cfg
setup.py
conf/__init__.py
conf/podcaster.cfg
data/__init__.py
podcaster/__init__.py
podcaster/app.py
podcaster/dates.py
podcaster/feed.py
podcaster/models.py
podcaster/renderers.py
podcaster.egg-info/PKG-INFO
podcaster.egg-info/SOURCES.txt
podcaster.egg-info/dependency_links.txt
podcaster.egg-info/entry_points.txt
podcaster.egg-info/not-zip-safe
podcaster.egg-info/requires.txt
podcaster.egg-info/top_level.txt
podcaster/platforms/__init__.py
podcaster/platforms/base.py
podcaster/platforms/youtube.py
static/__init__.py
static/css/bootstrap-responsive.min.css
static/css/bootstrap.min.css
static/img/glyphicons-halflings-white.png
static/img/glyphicons-halflings.png