Metadata-Version: 1.0
Name: podcaster
Version: 0.0.8
Summary: Podcaster is a Nagare application used to convert a youtube channel to an itunes podcast.
Home-page: https://bitbucket.org/droodle/podcaster
Author: Pierre Meyer
Author-email: meyer.p@gmail.com
License: BSD
Keywords: Nagare Youtube iTunes podcast RSS
Platform: UNKNOWN
Classifier: Development Status :: 4 - Beta
Classifier: License :: OSI Approved :: BSD License
Classifier: Programming Language :: Python
